sortedcontainers-stubs/__init__.pyi
sortedcontainers-stubs/_typing.pyi
sortedcontainers-stubs/sorteddict.pyi
sortedcontainers-stubs/sortedlist.pyi
sortedcontainers-stubs/sortedset.pyi
sortedcontainers_stubs-2.4.3.dist-info/LICENSE
sortedcontainers_stubs-2.4.3.dist-info/METADATA
sortedcontainers_stubs-2.4.3.dist-info/WHEEL
sortedcontainers_stubs-2.4.3.dist-info/RECORD
