Metadata-Version: 2.3
Name: sortedcontainers-stubs
Version: 2.4.3
Summary: Type stubs for sortedcontainers
License: Apache-2.0
Author: Hal Blackburn
Author-email: hwtb2@cam.ac.uk
Maintainer: Hal Blackburn
Maintainer-email: hwtb2@cam.ac.uk
Requires-Python: >=3.9,<4.0
Classifier: License :: OSI Approved :: Apache Software License
Classifier: Programming Language :: Python :: 3
Classifier: Programming Language :: Python :: 3.9
Classifier: Programming Language :: Python :: 3.10
Classifier: Programming Language :: Python :: 3.11
Classifier: Programming Language :: Python :: 3.12
Classifier: Programming Language :: Python :: 3.13
Classifier: Typing :: Stubs Only
Requires-Dist: sortedcontainers (>=2,<3)
Requires-Dist: typing-extensions (>=4.1.0,<5.0.0)
Project-URL: Changes, https://github.com/h4l/sortedcontainers-stubs/blob/main/CHANGELOG.md
Project-URL: Homepage, https://github.com/h4l/sortedcontainers-stubs
Project-URL: Issues, https://github.com/h4l/sortedcontainers-stubs/issues
Project-URL: Repository, https://github.com/h4l/sortedcontainers-stubs
